nvdu/__init__.py
nvdu/core/__init__.py
nvdu/core/box.py
nvdu/core/camera.py
nvdu/core/cuboid.py
nvdu/core/mesh.py
nvdu/core/nvdu_data.py
nvdu/core/pivot_axis.py
nvdu/core/scene_object.py
nvdu/core/transform3d.py
nvdu/core/utils3d.py
nvdu/tools/__init__.py
nvdu/tools/nvdu_ycb.py
nvdu/tools/test_nvdu_visualizer.py
nvdu/viz/__init__.py
nvdu/viz/background_image.py
nvdu/viz/camera.py
nvdu/viz/cuboid.py
nvdu/viz/image_draw.py
nvdu/viz/mesh.py
nvdu/viz/nvdu_visualizer.py
nvdu/viz/nvdu_viz_window.py
nvdu/viz/pivot_axis.py
nvdu/viz/scene.py
nvdu/viz/scene_object.py
nvdu/viz/utils3d.py
nvdu/viz/viewport.py
nvdu-1.0.0.0.data/data/nvdu_config/_ycb_aligned_cm.json
nvdu-1.0.0.0.data/data/nvdu_config/_ycb_aligned_m.json
nvdu-1.0.0.0.data/data/nvdu_config/_ycb_original.json
nvdu-1.0.0.0.dist-info/METADATA
nvdu-1.0.0.0.dist-info/RECORD
nvdu-1.0.0.0.dist-info/WHEEL
nvdu-1.0.0.0.dist-info/entry_points.txt
nvdu-1.0.0.0.dist-info/top_level.txt
