Metadata-Version: 2.1
Name: nvdu
Version: 1.0.0.0
Summary: Nvidia Dataset Utilities
Home-page: https://github.com/NVIDIA/Dataset_Utilities
Author: NVIDIA Corporation
Author-email: info@nvidia.com
Maintainer: Thang To
Maintainer-email: thangt@nvidia.com
License: Creative Commons Attribution-NonCommercial-ShareAlike 4.0. https://creativecommons.org/licenses/by-nc-sa/4.0/
Keywords: nvdu,nvidia
Platform: UNKNOWN
Classifier: Development Status :: 5 - Production/Stable
Classifier: Intended Audience :: Developers
Classifier: Natural Language :: English
Classifier: Operating System :: OS Independent
Classifier: Programming Language :: Python :: 3.6
Classifier: Topic :: Utilities
Classifier: Topic :: Software Development :: Libraries :: Python Modules
Requires-Dist: numpy
Requires-Dist: opencv-python
Requires-Dist: pyrr
Requires-Dist: PyWavefront (==0.2.0)
Requires-Dist: pyglet
Requires-Dist: fuzzyfinder
